{"id":"7r19ocenohkhv5aqltxrjtr","title":"Brain","desc":"","updated":1663099480085,"created":1662399580358,"custom":{},"fname":"health.brain","type":"note","vault":{"fsPath":".","selfContained":true,"name":"Content"},"contentHash":"d31869473bef4ef5edb7a6c629602aef","links":[],"anchors":{"intelligence":{"type":"header","text":"Intelligence","value":"intelligence","line":8,"column":0,"depth":2},"cognitive-biases":{"type":"header","text":"Cognitive biases","value":"cognitive-biases","line":12,"column":0,"depth":1}},"children":[],"parent":"dxwd5gga585h8x70d34wo05","data":{}}
